slm_graph/__init__.py
slm_graph/core.py
slm_graph/renderer.py
slm_graph/schema.py
slm_graph-0.1.2.dist-info/licenses/LICENCE
slm_graph-0.1.2.dist-info/METADATA
slm_graph-0.1.2.dist-info/WHEEL
slm_graph-0.1.2.dist-info/RECORD
