Metadata-Version: 2.4
Name: slm-graph
Version: 0.1.2
Summary: Self-contained natural language to Mermaid graph generator using SLMs.
License: MIT
License-File: LICENCE
Keywords: mermaid,llm,slm,graph,visualization,instructor
Author: Keegan001
Requires-Python: >=3.9,<4.0
Classifier: License :: OSI Approved :: MIT License
Classifier: Programming Language :: Python :: 3
Classifier: Programming Language :: Python :: 3.9
Classifier: Programming Language :: Python :: 3.10
Classifier: Programming Language :: Python :: 3.11
Classifier: Programming Language :: Python :: 3.12
Classifier: Programming Language :: Python :: 3.13
Classifier: Programming Language :: Python :: 3.14
Requires-Dist: instructor (>=1.3.0,<2.0.0)
Requires-Dist: llama-cpp-python (>=0.2.77,<0.3.0)
Requires-Dist: pydantic (>=2.0.0,<3.0.0)
